main.py
GrvB-0.2.dist-info/METADATA
GrvB-0.2.dist-info/WHEEL
GrvB-0.2.dist-info/top_level.txt
GrvB-0.2.dist-info/RECORD
