Metadata-Version: 2.1
Name: GrvB
Version: 0.2
Summary: This is speech to text package created by Gourav Barnwal
Author: Gourav Barnwal
Author-email: barnwalgourav547@gmail.com
